tinty/__init__.py
tinty/cli.py
tinty/color_codes.py
tinty/colors.py
tinty/enhanced.py
tinty/tinty.py
tinty-0.1.10.dist-info/LICENSE
tinty-0.1.10.dist-info/METADATA
tinty-0.1.10.dist-info/WHEEL
tinty-0.1.10.dist-info/entry_points.txt
tinty-0.1.10.dist-info/RECORD
