Metadata-Version: 2.1
Name: tinty
Version: 0.1.10
Summary: A Python library for terminal text colorization and highlighting
Home-page: https://github.com/jim-my/tinty
Keywords: color,terminal,ansi,highlighting,text,cli
Author: Jimmy
Requires-Python: >=3.9,<4.0
Classifier: Development Status :: 4 - Beta
Classifier: Environment :: Console
Classifier: Intended Audience :: Developers
Classifier: License :: OSI Approved :: MIT License
Classifier: Operating System :: OS Independent
Classifier: Programming Language :: Python :: 3
Classifier: Programming Language :: Python :: 3.9
Classifier: Programming Language :: Python :: 3.10
Classifier: Programming Language :: Python :: 3.11
Classifier: Programming Language :: Python :: 3.12
Classifier: Topic :: Software Development :: Libraries :: Python Modules
Classifier: Topic :: Terminals
Classifier: Topic :: Text Processing
Classifier: Topic :: Utilities
Provides-Extra: cli
Requires-Dist: click (>=8.0,<9.0) ; extra == "cli"
Project-URL: Documentation, https://github.com/jim-my/tinty
Project-URL: Repository, https://github.com/jim-my/tinty
